{"name":"Zenbones Rosebones Light","colors":{"selection.background":"#EADDDC","descriptionForeground":"#724341","errorForeground":"#B5637A","icon.foreground":"#724341a0","window.activeBorder":"#917BA9","window.inactiveBorder":"#724341","activityBar.foreground":"#724341","activityBar.background":"#ECD0A9","activityBarBadge.background":"#917BA9","activityBarBadge.foreground":"#F3E3CF","button.background":"#ECD0A9","button.foreground":"#724341","button.secondaryForeground":"#AE6966","button.secondaryBackground":"#F3E3CF","checkbox.background":"#ECD0A9","checkbox.foreground":"#724341","editorGroupHeader.tabsBackground":"#F3E3CF","tab.activeForeground":"#724341","tab.activeBackground":"#FBF6F0","tab.inactiveForeground":"#724341a0","tab.inactiveBackground":"#ECD0A9","tab.border":"#F3E3CF","panel.background":"#FBF6F0","panel.border":"#B69A6Ea0","panelTitle.activeBorder":"#B69A6Ea0","panelTitle.activeForeground":"#724341","panelTitle.inactiveForeground":"#724341a0","statusBar.foreground":"#AE6966","statusBar.background":"#F3E3CF","statusBar.debuggingBackground":"#F3E3CF","statusBar.noFolderBackground":"#F3E3CF","statusBarItem.remoteForeground":"#724341","statusBarItem.remoteBackground":"#ECD0A9","editor.foreground":"#724341","editor.background":"#FBF6F0","editor.lineHighlightBackground":"#F7ECE0","editor.selectionBackground":"#EADDDC","editorCursor.foreground":"#724341","editorIndentGuide.activeBackground":"#B69A6Ea0","editorIndentGuide.background":"#B69A6E50","editorLineNumber.activeForeground":"#724341","editorLineNumber.foreground":"#B69A6E","scrollbarSlider.activeBackground":"#C5A778","scrollbar.shadow":"#ECD0A9","notificationsInfoIcon.foreground":"#5795A0","notificationsWarningIcon.foreground":"#EC9D33","notificationsErrorIcon.foreground":"#B5637A","notificationLink.foreground":"#917BA9","editorBracketHighlight.foreground1":"#5795A0","notifications.background":"#FBF6F0","notifications.foreground":"#724341","notificationCenterHeader.background":"#F3E3CF","notificationCenterHeader.foreground":"#AE6966","badge.background":"#917BA9","badge.foreground":"#F3E3CF","terminal.ansiGreen":"#286A84","terminal.ansiCyan":"#5795A0","terminal.ansiBrightYellow":"#C68223","terminal.ansiBrightWhite":"#A4635F","terminal.ansiBrightRed":"#A54A66","terminal.ansiBrightMagenta":"#855AAC","terminal.ansiBrightGreen":"#1C5970","terminal.ansiBrightCyan":"#407D88","problemsWarningIcon.foreground":"#EC9D33","textLink.activeForeground":"#917BA9d0","editorGutter.modifiedBackground":"#D6E9ED","editorGutter.addedBackground":"#DDE7ED","textLink.foreground":"#917BA9","input.background":"#FBF6F0","input.foreground":"#724341","input.placeholderForeground":"#A18E72","inputOption.activeBorder":"#917BA9","inputValidation.errorBorder":"#B5637A","inputValidation.infoBorder":"#5795A0","inputValidation.warningBorder":"#EC9D33","sideBar.background":"#F3E3CF","sideBar.foreground":"#AE6966","sideBarSectionHeader.background":"#ECD0A9","sideBarSectionHeader.foreground":"#724341","minimap.findMatchHighlight":"#D1C9DC","minimap.selectionHighlight":"#EADDDC","minimap.errorHighlight":"#B5637A","minimap.warningHighlight":"#EC9D33","minimapGutter.addedBackground":"#DDE7ED","minimapGutter.modifiedBackground":"#D6E9ED","minimapGutter.deletedBackground":"#F0E2E5","pickerGroup.border":"#B69A6Ea0","pickerGroup.foreground":"#AE6966","quickInput.background":"#F3E3CF","quickInput.foreground":"#AE6966","quickInputList.focusBackground":"#ECD0A9","quickInputList.focusForeground":"#724341","keybindingLabel.background":"#ECD0A9","keybindingLabel.foreground":"#724341","keybindingLabel.border":"#EED7B7","keybindingLabel.bottomBorder":"#DEBC88","list.activeSelectionBackground":"#DEBC88","list.activeSelectionForeground":"#724341","list.highlightForeground":"#917BA9","list.hoverBackground":"#DEBC8850","list.inactiveSelectionBackground":"#DEBC88a0","editorRuler.foreground":"#B69A6Ea0","editor.findMatchBackground":"#A18EB6","editor.findMatchHighlightBackground":"#D1C9DC","editorOverviewRuler.findMatchForeground":"#D1C9DC","editorOverviewRuler.selectionHighlightForeground":"#EADDDC","editorOverviewRuler.modifiedForeground":"#D6E9ED","editorOverviewRuler.addedForeground":"#DDE7ED","editorOverviewRuler.deletedForeground":"#F0E2E5","editorOverviewRuler.errorForeground":"#B5637A","editorOverviewRuler.warningForeground":"#EC9D33","editorOverviewRuler.infoForeground":"#5795A0","editorError.foreground":"#B5637A","editorWarning.foreground":"#EC9D33","editorInfo.foreground":"#5795A0","editorHint.foreground":"#917BA9","problemsErrorIcon.foreground":"#B5637A","scrollbarSlider.hoverBackground":"#DEBC88","terminal.ansiBlack":"#FBF6F0","terminal.ansiBlue":"#5795A0","terminal.ansiBrightBlack":"#E8C48B","terminal.ansiBrightBlue":"#407D88","editorWidget.foreground":"#AE6966","editorWidget.background":"#F3E3CF","editorWidget.border":"#ECD0A9","editorHoverWidget.foreground":"#724341","editorHoverWidget.background":"#EED7B7","editorHoverWidget.border":"#DEBC88","terminal.ansiMagenta":"#917BA9","terminal.ansiRed":"#B5637A","terminal.ansiWhite":"#724341","terminal.ansiYellow":"#EC9D33","terminalCursor.background":"#FBF6F0","terminalCursor.foreground":"#724341","foreground":"#724341","editorBracketHighlight.foreground2":"#286A84","editorBracketHighlight.foreground3":"#917BA9","editorBracketHighlight.foreground4":"#5795A0","editorBracketHighlight.foreground5":"#286A84","editorBracketHighlight.foreground6":"#917BA9","editorBracketHighlight.unexpectedBracket.foreground":"#B5637A","scrollbarSlider.background":"#EED7B7","editorGutter.deletedBackground":"#F0E2E5","focusBorder":"#917BA9","disabledForeground":"#72434180","problemsInfoIcon.foreground":"#5795A0","widget.shadow":"#ECD0A9"},"tokenColors":[{"name":"Comment","scope":["comment"],"settings":{"fontStyle":"italic","foreground":"#A18E72"}},{"name":"Constant","scope":["variable.other.constant","constant","string"],"settings":{"fontStyle":"italic","foreground":"#AB6763"}},{"name":"Number","scope":["constant.numeric"],"settings":{"fontStyle":"italic","foreground":"#724341"}},{"name":"Boolean","scope":["constant.language.boolean"],"settings":{"fontStyle":"italic","foreground":"#724341"}},{"name":"Identifier","scope":["variable.other"],"settings":{"fontStyle":"","foreground":"#935855"}},{"name":"Function","scope":["entity.name.function"],"settings":{"fontStyle":"","foreground":"#724341"}},{"name":"Statement","scope":["keyword"],"settings":{"fontStyle":"","foreground":"#286A84"}},{"name":"PreProc","scope":["keyword.control.directive"],"settings":{"fontStyle":"bold","foreground":"#724341"}},{"name":"Type","scope":["storage.type","storage.modifier","keyword.other.typedef"],"settings":{"fontStyle":"","foreground":"#57527A"}},{"name":"Special","scope":["punctuation.definition.template-expression"],"settings":{"fontStyle":"","foreground":"#5795A0"}},{"name":"Tag","scope":["entity.name.tag"],"settings":{"fontStyle":"","foreground":"#5795A0"}},{"name":"PropertyName","scope":["support.type.property-name"],"settings":{"fontStyle":"italic","foreground":"#724341"}}],"type":"light"}
